pytraph/__init__.py
pytraph/core/__init__.py
pytraph/core/_traph_tensor.pyd
pytraph/core/dtype.py
pytraph/core/tensor.py
pytraph/core/traph_tensor.py
pytraph-0.0.1.dist-info/METADATA
pytraph-0.0.1.dist-info/WHEEL
pytraph-0.0.1.dist-info/top_level.txt
pytraph-0.0.1.dist-info/RECORD
